cro3n-0.0.4.dist-info/METADATA
cro3n-0.0.4.dist-info/WHEEL
cro3n-0.0.4.dist-info/license_files/LICENSE
cro3n/__init__.py
cro3n/cro3n.pypy39-pp73-s390x-linux-gnu.so
cro3n-0.0.4.dist-info/RECORD
