Metadata-Version: 2.1
Name: cro3n
Version: 0.0.4
Classifier: Development Status :: 1 - Planning
Classifier: Programming Language :: Python :: 3 :: Only
Classifier: Programming Language :: Python :: 3.7
Classifier: Programming Language :: Python :: 3.8
Classifier: Programming Language :: Python :: 3.9
Classifier: Programming Language :: Python :: 3.10
Classifier: Programming Language :: Python :: Implementation :: CPython
Classifier: Programming Language :: Python :: Implementation :: PyPy
Classifier: Programming Language :: Rust
Classifier: License :: OSI Approved :: MIT License
License-File: LICENSE
Summary: Another one **cron expression** utils package for python
Author-email: straydragon <straydragonv@gmail.com>
Requires-Python: >=3.7
Project-URL: Homepage, https://github.com/straydragon/cro3n
Project-URL: Bug Tracker, https://github.com/straydragon/cro3n/issues
